torchblaze/__init__.py
torchblaze/__main__.py
torchblaze/apitests.py
torchblaze/dockerise.py
torchblaze/mltests.py
torchblaze/template.py
torchblaze/template_files/README.txt
torchblaze/template_files/app.py
torchblaze/template_files/docker.txt
torchblaze/template_files/model.py
torchblaze/template_files/procfile.txt
torchblaze/template_files/requirements.txt
torchblaze/template_files/tests.txt
torchblaze/template_files/train.py
torchblaze/template_files/utils.py
torchblaze-1.0.6.dist-info/LICENSE
torchblaze-1.0.6.dist-info/METADATA
torchblaze-1.0.6.dist-info/WHEEL
torchblaze-1.0.6.dist-info/entry_points.txt
torchblaze-1.0.6.dist-info/top_level.txt
torchblaze-1.0.6.dist-info/RECORD
