Metadata-Version: 2.1
Name: torchblaze
Version: 1.0.6
Summary: A CLI-based python package that provides a suite of functionalities to perform end-to-end ML using PyTorch.
Home-page: https://github.com/MLH-Fellowship/torchblaze
Author: Sai Durga Kamesh Kota
Author-email: ksdkamesh99@gmail.com
License: MIT
Platform: UNKNOWN
Classifier: License :: OSI Approved :: MIT License
Classifier: Programming Language :: Python :: 2.7
Classifier: Programming Language :: Python :: 3
Classifier: Programming Language :: Python :: 3.7
Requires-Python: >=3.7.0
Requires-Dist: fire (==0.4.0)
Requires-Dist: flask
Requires-Dist: requests
